setup.py
backspinpy/Cef_tools.py
backspinpy/__init__.py
backspinpy/backSPIN.py
backspinpy/backspin
backspinpy.egg-info/PKG-INFO
backspinpy.egg-info/SOURCES.txt
backspinpy.egg-info/dependency_links.txt
backspinpy.egg-info/requires.txt
backspinpy.egg-info/top_level.txt