Metadata-Version: 1.0
Name: backspinpy
Version: 0.2.1
Summary: backSPIN clustering algorythm
Home-page: https://github.com/linnarsson-lab/BackSPIN
Author: Linnarsson Lab
Author-email: gioelelamanno@gmail.com
License: MIT
Platform: UNKNOWN
